{
  "wp": null,
  "lw": null,
  "orl": [
    5,
    8,
    7,
    3,
    6,
    6,
    7,
    4,
    8,
    7,
    4,
    2,
    10,
    4,
    2,
    5,
    9,
    5,
    5,
    9,
    4,
    7,
    8,
    9,
    3,
    5,
    9,
    6,
    10,
    4,
    2,
    5,
    10,
    7,
    2
  ],
  "snww": null,
  "ssb": {
    "1": 9,
    "2": 10,
    "3": 25
  },
  "ss": {
    "1": 9,
    "2": 10,
    "3": 25
  },
  "fs": null,
  "rs": {
    "sspt": {
      "3": {
        "op": 24,
        "np": 25
      }
    },
    "rns": [
      [
        5
      ],
      [
        4
      ],
      [
        2,
        5
      ],
      [
        7
      ],
      []
    ],
    "rnss": [
      [],
      [],
      [],
      [],
      []
    ],
    "bsb": []
  },
  "ssaw": 4.8,
  "ptbr": null,
  "sc": 0,
  "mi": 1,
  "wm": 2,
  "lwa": 0,
  "gwt": -1,
  "pmt": null,
  "ab": null,
  "ml": 2,
  "cs": 0.3,
  "rl": [
    5,
    8,
    7,
    3,
    6,
    6,
    7,
    4,
    8,
    7,
    4,
    2,
    10,
    4,
    2,
    5,
    9,
    5,
    5,
    9,
    4,
    7,
    8,
    9,
    3,
    5,
    9,
    6,
    10,
    4,
    2,
    5,
    10,
    7,
    2
  ],
  "ctw": 0,
  "cwc": 0,
  "fstc": {
    "4": 1
  },
  "pcwc": 0,
  "rwsp": null,
  "hashr": "1:5;4;2;7;10#8;8;5;8;4#7;7;9;9;2#3;4;5;3;5#6;2;5;5;10#6;10;9;9;7#7;4;4;6;2#MV#0#MT#1#MG#0#",
  "fb": null,
  "sid": "1981102606025489920",
  "psid": "1981102590770806272",
  "st": 4,
  "nst": 1,
  "pf": 2,
  "aw": 4.8,
  "wid": 0,
  "wt": "C",
  "wk": "0_C",
  "wbn": null,
  "wfg": null,
  "blb": 102323.2,
  "blab": 102323.2,
  "bl": 102323.2,
  "tb": 0,
  "tbb": 12,
  "tw": 0,
  "np": 0,
  "ocr": null,
  "mr": null,
  "ge": [
    1,
    11
  ]
}