{
  "wp": {
    "8": [
      2,
      6,
      9
    ],
    "9": [
      2,
      6,
      10
    ]
  },
  "lw": {
    "8": 1.8,
    "9": 1.8
  },
  "orl": [
    2,
    2,
    6,
    99,
    6,
    6,
    0,
    5,
    6,
    6,
    6,
    99
  ],
  "ift": false,
  "iff": false,
  "cpf": {},
  "cptw": 0,
  "crtw": 0,
  "imw": false,
  "fs": null,
  "gwt": -1,
  "pmt": null,
  "ab": null,
  "ml": 2,
  "cs": 0.3,
  "rl": [
    2,
    2,
    6,
    99,
    6,
    6,
    0,
    5,
    6,
    6,
    6,
    99
  ],
  "ctw": 3.6,
  "cwc": 1,
  "fstc": null,
  "pcwc": 1,
  "rwsp": {
    "8": 3,
    "9": 3
  },
  "hashr": "0:2;6;6#2;6;6#6;0;6#99;5;99#R#6#021221#MV#6.0#MT#1#R#6#021222#MV#6.0#MT#1#MG#3.6#",
  "fb": null,
  "sid": "1983617309482155520",
  "psid": "1983617309482155520",
  "st": 1,
  "nst": 1,
  "pf": 2,
  "aw": 3.6,
  "wid": 0,
  "wt": "C",
  "wk": "0_C",
  "wbn": null,
  "wfg": null,
  "blb": 116967.4,
  "blab": 116961.4,
  "bl": 116965,
  "tb": 6,
  "tbb": 6,
  "tw": 3.6,
  "np": -2.4,
  "ocr": null,
  "mr": null,
  "ge": [
    1,
    11
  ]
}