{
  "wp": null,
  "lw": null,
  "orl": [
    7,
    8,
    7,
    8,
    7,
    9,
    8,
    10,
    10,
    10,
    5,
    5,
    0,
    10,
    4,
    5,
    5,
    9,
    3,
    9,
    2,
    6,
    9,
    2,
    9,
    7,
    5,
    9,
    8,
    7,
    5,
    10,
    7,
    5,
    10
  ],
  "snww": null,
  "ssb": {
    "1": 11,
    "3": 15,
    "4": 16,
    "5": 17,
    "6": 18,
    "8": 19,
    "9": 20,
    "10": 14
  },
  "ss": {
    "1": 11,
    "3": 15,
    "4": 16,
    "5": 17,
    "6": 18,
    "8": 19,
    "9": 20,
    "10": 14
  },
  "fs": {
    "aw": 744,
    "s": 2,
    "ts": 10,
    "nosa": 0
  },
  "rs": {
    "sspt": {
      "3": {
        "op": 14,
        "np": 15
      },
      "4": {
        "op": 15,
        "np": 16
      },
      "5": {
        "op": 16,
        "np": 17
      },
      "6": {
        "op": 17,
        "np": 18
      }
    },
    "rns": [
      [
        7,
        8
      ],
      [],
      [
        4
      ],
      [
        6
      ],
      []
    ],
    "rnss": [
      [],
      [],
      [
        0
      ],
      [],
      []
    ],
    "bsb": []
  },
  "ssaw": 48,
  "ptbr": null,
  "sc": 0,
  "mi": 2,
  "wm": 6,
  "lwa": 0,
  "gwt": -1,
  "pmt": null,
  "ab": null,
  "ml": 2,
  "cs": 0.3,
  "rl": [
    7,
    8,
    7,
    8,
    7,
    9,
    8,
    10,
    10,
    10,
    5,
    5,
    0,
    10,
    4,
    5,
    5,
    9,
    3,
    9,
    2,
    6,
    9,
    2,
    9,
    7,
    5,
    9,
    8,
    7,
    5,
    10,
    7,
    5,
    10
  ],
  "ctw": 0,
  "cwc": 0,
  "fstc": {
    "21": 8,
    "22": 11
  },
  "pcwc": 0,
  "rwsp": null,
  "hashr": "19:7;10;4;6;8#8;10;5;9;7#7;10;5;2;5#8;5;9;9;10#7;5;3;7;7#9;0;9;5;5#8;10;2;9;10#MV#0#MT#1#MG#0#",
  "fb": null,
  "sid": "1981143339625348608",
  "psid": "1981143009403600384",
  "st": 22,
  "nst": 21,
  "pf": 2,
  "aw": 744,
  "wid": 0,
  "wt": "C",
  "wk": "0_C",
  "wbn": null,
  "wfg": null,
  "blb": 117609.4,
  "blab": 117609.4,
  "bl": 117609.4,
  "tb": 0,
  "tbb": 12,
  "tw": 0,
  "np": 0,
  "ocr": null,
  "mr": null,
  "ge": [
    1,
    11
  ]
}