{
  "wp": {
    "2": [
      4,
      11,
      18,
      24
    ],
    "3": [
      1,
      8,
      17,
      18
    ]
  },
  "lw": {
    "2": 15,
    "3": 9.6
  },
  "orl": [
    5,
    3,
    6,
    10,
    2,
    6,
    10,
    4,
    3,
    7,
    5,
    2,
    8,
    7,
    4,
    10,
    8,
    3,
    0,
    10,
    8,
    7,
    10,
    7,
    2,
    10,
    7,
    9,
    9,
    6,
    8,
    4,
    9,
    6,
    3
  ],
  "snww": {
    "2": 1,
    "3": 2
  },
  "ssb": {
    "1": 10,
    "2": 13,
    "3": 15
  },
  "ss": {
    "1": 10,
    "2": 13,
    "3": 15
  },
  "fs": null,
  "rs": {
    "sspt": {},
    "rns": [
      [
        5
      ],
      [
        4
      ],
      [],
      [],
      []
    ],
    "rnss": [
      [],
      [],
      [],
      [],
      []
    ],
    "bsb": []
  },
  "ssaw": 49.8,
  "ptbr": [
    4,
    11,
    18,
    24,
    1,
    8,
    17
  ],
  "sc": 0,
  "mi": 1,
  "wm": 2,
  "lwa": 24.6,
  "gwt": 1,
  "pmt": null,
  "ab": null,
  "ml": 2,
  "cs": 0.3,
  "rl": [
    5,
    3,
    6,
    10,
    2,
    6,
    10,
    4,
    3,
    7,
    5,
    2,
    8,
    7,
    4,
    10,
    8,
    3,
    0,
    10,
    8,
    7,
    10,
    7,
    2,
    10,
    7,
    9,
    9,
    6,
    8,
    4,
    9,
    6,
    3
  ],
  "ctw": 49.2,
  "cwc": 2,
  "fstc": {
    "4": 1
  },
  "pcwc": 0,
  "rwsp": {
    "2": 25,
    "3": 8
  },
  "hashr": "1:5;4;4;7;9#3;3;10;10;6#6;7;8;7;8#10;5;3;2;4#2;2;0;10;9#6;8;10;7;6#10;7;8;9;3#R#2#04142433#MV#0#MT#1#R#3#01112324#MV#0#MT#1#MG#49.2#",
  "fb": null,
  "sid": "1981145364081671680",
  "psid": "1981145348969594368",
  "st": 4,
  "nst": 4,
  "pf": 2,
  "aw": 49.8,
  "wid": 0,
  "wt": "C",
  "wk": "0_C",
  "wbn": null,
  "wfg": null,
  "blb": 117438.4,
  "blab": 117438.4,
  "bl": 117487.6,
  "tb": 0,
  "tbb": 12,
  "tw": 49.2,
  "np": 49.2,
  "ocr": null,
  "mr": null,
  "ge": [
    1,
    11
  ]
}