{
  "wp": {
    "10": [
      3,
      8,
      17
    ]
  },
  "lw": {
    "10": 0.6
  },
  "orl": [
    4,
    5,
    7,
    10,
    9,
    9,
    10,
    3,
    10,
    5,
    6,
    8,
    8,
    1,
    8,
    9,
    7,
    10,
    6,
    7,
    10,
    5,
    7,
    7,
    2,
    5,
    7,
    5,
    6,
    9,
    8,
    6,
    8,
    9,
    9
  ],
  "snww": {
    "10": 1
  },
  "ssb": {
    "1": 8,
    "2": 15,
    "3": 18,
    "4": 19,
    "5": 20
  },
  "ss": {
    "2": 15,
    "3": 18,
    "4": 19,
    "5": 20
  },
  "fs": null,
  "rs": null,
  "ssaw": 0.6,
  "ptbr": [
    3,
    17
  ],
  "sc": 0,
  "mi": 0,
  "wm": 1,
  "lwa": 0.6,
  "gwt": -1,
  "pmt": null,
  "ab": null,
  "ml": 2,
  "cs": 0.3,
  "rl": [
    4,
    5,
    7,
    10,
    9,
    9,
    10,
    3,
    0,
    5,
    6,
    8,
    8,
    1,
    8,
    9,
    7,
    10,
    6,
    7,
    10,
    5,
    7,
    7,
    2,
    5,
    7,
    5,
    6,
    9,
    8,
    6,
    8,
    9,
    9
  ],
  "ctw": 0.6,
  "cwc": 1,
  "fstc": null,
  "pcwc": 1,
  "rwsp": {
    "10": 1
  },
  "hashr": "0:4;3;8;5;6#5;0;9;7;9#7;5;7;7;8#10;6;10;2;6#9;8;6;5;8#9;8;7;7;9#10;1;10;5;9#R#10#031123#MV#12.0#MT#1#MG#0.6#",
  "fb": null,
  "sid": "1981179316251131392",
  "psid": "1981179316251131392",
  "st": 1,
  "nst": 4,
  "pf": 2,
  "aw": 0.6,
  "wid": 0,
  "wt": "C",
  "wk": "0_C",
  "wbn": null,
  "wfg": null,
  "blb": 129013,
  "blab": 129001,
  "bl": 129001.6,
  "tb": 12,
  "tbb": 12,
  "tw": 0.6,
  "np": -11.4,
  "ocr": null,
  "mr": null,
  "ge": [
    1,
    11
  ]
}