{
  "wp": {
    "9": [
      3,
      8,
      15,
      19,
      23,
      24,
      26
    ]
  },
  "lw": {
    "9": 10.8
  },
  "orl": [
    10,
    2,
    3,
    9,
    6,
    7,
    6,
    5,
    9,
    10,
    10,
    8,
    2,
    10,
    5,
    9,
    10,
    5,
    8,
    9,
    7,
    8,
    8,
    9,
    9,
    6,
    9,
    6,
    9,
    5,
    7,
    10,
    2,
    5,
    10
  ],
  "snww": {
    "9": 6
  },
  "ssb": {
    "1": 12,
    "2": 16,
    "3": 20,
    "4": 22,
    "5": 24,
    "6": 26
  },
  "ss": {
    "1": 12,
    "2": 16,
    "3": 20,
    "4": 22
  },
  "fs": null,
  "rs": null,
  "ssaw": 10.8,
  "ptbr": [
    3,
    8,
    15,
    19,
    23
  ],
  "sc": 0,
  "mi": 0,
  "wm": 1,
  "lwa": 10.8,
  "gwt": -1,
  "pmt": null,
  "ab": null,
  "ml": 2,
  "cs": 0.3,
  "rl": [
    10,
    2,
    3,
    9,
    6,
    7,
    6,
    5,
    9,
    10,
    10,
    8,
    2,
    10,
    5,
    9,
    10,
    5,
    8,
    9,
    7,
    8,
    8,
    9,
    0,
    6,
    0,
    6,
    9,
    5,
    7,
    10,
    2,
    5,
    10
  ],
  "ctw": 10.8,
  "cwc": 1,
  "fstc": null,
  "pcwc": 1,
  "rwsp": {
    "9": 3
  },
  "hashr": "0:10;5;5;8;9#2;9;9;8;5#3;10;10;9;7#9;10;5;0;10#6;8;8;6;2#7;2;9;0;5#6;10;7;6;10#R#9#03112125323335#MV#12.0#MT#1#MG#10.8#",
  "fb": null,
  "sid": "1981358403640884736",
  "psid": "1981358403640884736",
  "st": 1,
  "nst": 4,
  "pf": 2,
  "aw": 10.8,
  "wid": 0,
  "wt": "C",
  "wk": "0_C",
  "wbn": null,
  "wfg": null,
  "blb": 146608.6,
  "blab": 146596.6,
  "bl": 146607.4,
  "tb": 12,
  "tbb": 12,
  "tw": 10.8,
  "np": -1.2,
  "ocr": null,
  "mr": null,
  "ge": [
    1,
    11
  ]
}