{
  "wp": {
    "6": [
      1,
      4,
      12,
      16,
      22,
      26
    ]
  },
  "lw": {
    "6": 12
  },
  "orl": [
    7,
    6,
    3,
    3,
    6,
    7,
    6,
    7,
    5,
    10,
    5,
    8,
    0,
    10,
    5,
    5,
    6,
    5,
    5,
    8,
    7,
    7,
    6,
    8,
    8,
    8,
    6,
    6,
    1,
    9,
    5,
    7,
    2,
    5,
    10
  ],
  "snww": {
    "6": 4
  },
  "ssb": {
    "3": 20,
    "4": 25,
    "5": 21
  },
  "ss": {
    "3": 20,
    "4": 25,
    "5": 21
  },
  "fs": null,
  "rs": {
    "sspt": {},
    "rns": [
      [
        7
      ],
      [],
      [
        5
      ],
      [],
      []
    ],
    "rnss": [
      [],
      [],
      [],
      [],
      []
    ],
    "bsb": []
  },
  "ssaw": 117.6,
  "ptbr": [
    1,
    4,
    12,
    16,
    22,
    26
  ],
  "sc": 0,
  "mi": 3,
  "wm": 5,
  "lwa": 12,
  "gwt": 2,
  "pmt": null,
  "ab": null,
  "ml": 2,
  "cs": 0.3,
  "rl": [
    7,
    6,
    3,
    3,
    6,
    7,
    6,
    7,
    5,
    10,
    5,
    8,
    0,
    10,
    5,
    5,
    6,
    5,
    5,
    8,
    7,
    7,
    6,
    8,
    8,
    8,
    6,
    6,
    1,
    9,
    5,
    7,
    2,
    5,
    10
  ],
  "ctw": 60,
  "cwc": 4,
  "fstc": {
    "4": 3
  },
  "pcwc": 0,
  "rwsp": {
    "6": 5
  },
  "hashr": "3:7;7;5;7;1#6;5;5;6;9#3;10;6;8;5#3;5;5;8;7#6;8;5;8;2#7;0;8;6;5#6;10;7;6;10#R#6#010415223135#MV#0#MT#1#MG#60.0#",
  "fb": null,
  "sid": "1981358441905520128",
  "psid": "1981358403640884736",
  "st": 4,
  "nst": 4,
  "pf": 2,
  "aw": 117.6,
  "wid": 0,
  "wt": "C",
  "wk": "0_C",
  "wbn": null,
  "wfg": null,
  "blb": 146654.2,
  "blab": 146654.2,
  "bl": 146714.2,
  "tb": 0,
  "tbb": 12,
  "tw": 60,
  "np": 60,
  "ocr": null,
  "mr": null,
  "ge": [
    1,
    11
  ]
}