{
  "wp": {
    "6": [
      1,
      9,
      19,
      22
    ],
    "7": [
      2,
      4,
      9,
      19,
      23,
      29,
      32
    ],
    "8": [
      3,
      9,
      15,
      19,
      24
    ]
  },
  "lw": {
    "6": 3,
    "7": 28.8,
    "8": 4.8
  },
  "orl": [
    7,
    6,
    7,
    8,
    7,
    7,
    8,
    5,
    10,
    0,
    4,
    5,
    10,
    10,
    4,
    8,
    9,
    3,
    10,
    0,
    9,
    9,
    6,
    7,
    8,
    4,
    9,
    3,
    7,
    7,
    2,
    5,
    7,
    10,
    2
  ],
  "snww": {
    "6": 1,
    "7": 4,
    "8": 2
  },
  "ssb": {
    "2": 11,
    "3": 14,
    "5": 25,
    "6": 27
  },
  "ss": {
    "2": 11,
    "3": 14,
    "5": 25,
    "6": 27
  },
  "fs": null,
  "rs": {
    "sspt": {
      "5": {
        "op": 24,
        "np": 25
      }
    },
    "rns": [
      [
        7
      ],
      [],
      [],
      [
        9,
        6
      ],
      []
    ],
    "rnss": [
      [],
      [],
      [],
      [],
      []
    ],
    "bsb": []
  },
  "ssaw": 79.2,
  "ptbr": [
    1,
    9,
    19,
    22,
    2,
    4,
    23,
    29,
    32,
    3,
    15,
    24
  ],
  "sc": 0,
  "mi": 1,
  "wm": 2,
  "lwa": 36.6,
  "gwt": 2,
  "pmt": null,
  "ab": null,
  "ml": 2,
  "cs": 0.3,
  "rl": [
    7,
    6,
    7,
    8,
    7,
    7,
    8,
    5,
    10,
    0,
    4,
    5,
    10,
    10,
    4,
    8,
    9,
    3,
    10,
    0,
    9,
    9,
    6,
    7,
    8,
    4,
    9,
    3,
    7,
    7,
    2,
    5,
    7,
    10,
    2
  ],
  "ctw": 73.2,
  "cwc": 2,
  "fstc": {
    "4": 1
  },
  "pcwc": 0,
  "rwsp": {
    "6": 5,
    "7": 12,
    "8": 4
  },
  "hashr": "1:7;5;4;9;7#6;10;8;6;7#7;0;9;7;2#8;4;3;8;5#7;5;10;4;7#7;10;0;9;10#8;10;9;3;2#R#6#01122531#MV#0#MT#1#R#7#02041225324144#MV#0#MT#1#R#8#0312212533#MV#0#MT#1#MG#73.2#",
  "fb": null,
  "sid": "1981143479090150912",
  "psid": "1981143463843855872",
  "st": 4,
  "nst": 4,
  "pf": 2,
  "aw": 79.2,
  "wid": 0,
  "wt": "C",
  "wk": "0_C",
  "wbn": null,
  "wfg": null,
  "blb": 117519.4,
  "blab": 117519.4,
  "bl": 117592.6,
  "tb": 0,
  "tbb": 12,
  "tw": 73.2,
  "np": 73.2,
  "ocr": null,
  "mr": null,
  "ge": [
    1,
    11
  ]
}