{
  "wp": {
    "5": [
      2,
      3,
      9,
      16,
      24,
      26
    ],
    "10": [
      4,
      8,
      16,
      17,
      23
    ]
  },
  "lw": {
    "5": 24,
    "10": 3.6
  },
  "orl": [
    10,
    9,
    5,
    5,
    10,
    5,
    9,
    2,
    10,
    5,
    3,
    3,
    8,
    9,
    9,
    7,
    0,
    10,
    4,
    2,
    7,
    7,
    7,
    10,
    5,
    8,
    5,
    10,
    5,
    9,
    6,
    8,
    4,
    9,
    6
  ],
  "snww": {
    "5": 4,
    "10": 2
  },
  "ssb": {
    "2": 19,
    "3": 21,
    "4": 24,
    "5": 14
  },
  "ss": {
    "2": 19,
    "3": 21,
    "5": 14
  },
  "fs": null,
  "rs": {
    "sspt": {},
    "rns": [
      [
        10
      ],
      [
        2
      ],
      [],
      [],
      []
    ],
    "rnss": [
      [],
      [],
      [],
      [],
      []
    ],
    "bsb": []
  },
  "ssaw": 87,
  "ptbr": [
    2,
    3,
    9,
    16,
    26,
    4,
    8,
    17,
    23
  ],
  "sc": 0,
  "mi": 2,
  "wm": 3,
  "lwa": 27.6,
  "gwt": 2,
  "pmt": null,
  "ab": null,
  "ml": 2,
  "cs": 0.3,
  "rl": [
    10,
    9,
    5,
    5,
    10,
    5,
    9,
    2,
    10,
    5,
    3,
    3,
    8,
    9,
    9,
    7,
    0,
    10,
    4,
    2,
    7,
    7,
    7,
    10,
    0,
    8,
    5,
    10,
    5,
    9,
    6,
    8,
    4,
    9,
    6
  ],
  "ctw": 82.8,
  "cwc": 3,
  "fstc": {
    "4": 2
  },
  "pcwc": 0,
  "rwsp": {
    "5": 10,
    "10": 3
  },
  "hashr": "2:10;2;9;7;5#9;10;7;7;9#5;5;0;10;6#5;3;10;0;8#10;3;4;8;4#5;8;2;5;9#9;9;7;10;6#R#5#020312223335#MV#0#MT#1#R#10#0411222332#MV#0#MT#1#MG#82.8#",
  "fb": null,
  "sid": "1981152105498410496",
  "psid": "1981152080047373824",
  "st": 4,
  "nst": 4,
  "pf": 2,
  "aw": 87,
  "wid": 0,
  "wt": "C",
  "wk": "0_C",
  "wbn": null,
  "wfg": null,
  "blb": 121197.4,
  "blab": 121197.4,
  "bl": 121280.2,
  "tb": 0,
  "tbb": 12,
  "tw": 82.8,
  "np": 82.8,
  "ocr": null,
  "mr": null,
  "ge": [
    1,
    11
  ]
}