{
  "wp": null,
  "lw": null,
  "orl": [
    10,
    5,
    9,
    9,
    9,
    10,
    2,
    1,
    3,
    8,
    6,
    6,
    2,
    7,
    2,
    7,
    7,
    7,
    8,
    4,
    8,
    3,
    8,
    2,
    5,
    2,
    2,
    2,
    8,
    6,
    7,
    9,
    6,
    6,
    2
  ],
  "snww": null,
  "ssb": {
    "1": 10,
    "3": 19,
    "4": 20,
    "5": 27,
    "6": 22
  },
  "ss": {
    "1": 10,
    "3": 19,
    "4": 20,
    "5": 27,
    "6": 22
  },
  "fs": null,
  "rs": {
    "sspt": {},
    "rns": [
      [
        10
      ],
      [
        1
      ],
      [
        2
      ],
      [],
      []
    ],
    "rnss": [
      [],
      [],
      [],
      [],
      []
    ],
    "bsb": []
  },
  "ssaw": 191.4,
  "ptbr": null,
  "sc": 0,
  "mi": 3,
  "wm": 5,
  "lwa": 0,
  "gwt": -1,
  "pmt": null,
  "ab": null,
  "ml": 2,
  "cs": 0.3,
  "rl": [
    10,
    5,
    9,
    9,
    9,
    10,
    2,
    1,
    3,
    8,
    6,
    6,
    2,
    7,
    2,
    7,
    7,
    7,
    8,
    4,
    8,
    3,
    8,
    2,
    5,
    2,
    2,
    2,
    8,
    6,
    7,
    9,
    6,
    6,
    2
  ],
  "ctw": 0,
  "cwc": 0,
  "fstc": {
    "4": 3
  },
  "pcwc": 0,
  "rwsp": null,
  "hashr": "3:10;1;2;3;8#5;3;7;8;6#9;8;7;2;7#9;6;7;5;9#9;6;8;2;6#10;2;4;2;6#2;7;8;2;2#MV#0#MT#1#MG#0#",
  "fb": null,
  "sid": "1981332937576021504",
  "psid": "1981332897855962624",
  "st": 4,
  "nst": 1,
  "pf": 2,
  "aw": 191.4,
  "wid": 0,
  "wt": "C",
  "wk": "0_C",
  "wbn": null,
  "wfg": null,
  "blb": 133130.2,
  "blab": 133130.2,
  "bl": 133130.2,
  "tb": 0,
  "tbb": 12,
  "tw": 0,
  "np": 0,
  "ocr": null,
  "mr": null,
  "ge": [
    1,
    11
  ]
}