{
  "wp": {
    "8": [
      1,
      4,
      9,
      17,
      24,
      30
    ]
  },
  "lw": {
    "8": 12
  },
  "orl": [
    8,
    8,
    7,
    6,
    8,
    7,
    3,
    10,
    10,
    8,
    7,
    10,
    10,
    4,
    5,
    9,
    5,
    8,
    9,
    9,
    5,
    10,
    5,
    6,
    8,
    4,
    9,
    6,
    7,
    5,
    8,
    10,
    10,
    7,
    8
  ],
  "snww": {
    "8": 2
  },
  "ssb": {
    "1": 11,
    "2": 14,
    "3": 15,
    "4": 16,
    "5": 17,
    "6": 18,
    "7": 19,
    "8": 20
  },
  "ss": {
    "1": 11,
    "2": 14,
    "3": 15,
    "4": 16,
    "6": 18,
    "7": 19,
    "8": 20
  },
  "fs": {
    "aw": 24,
    "s": 11,
    "ts": 12,
    "nosa": 0
  },
  "rs": null,
  "ssaw": 24,
  "ptbr": [
    1,
    4,
    9,
    24,
    30
  ],
  "sc": 0,
  "mi": 0,
  "wm": 2,
  "lwa": 12,
  "gwt": -1,
  "pmt": null,
  "ab": null,
  "ml": 2,
  "cs": 0.3,
  "rl": [
    8,
    8,
    7,
    6,
    8,
    7,
    3,
    10,
    10,
    8,
    7,
    10,
    10,
    4,
    5,
    9,
    5,
    0,
    9,
    9,
    5,
    10,
    5,
    6,
    8,
    4,
    9,
    6,
    7,
    5,
    8,
    10,
    10,
    7,
    8
  ],
  "ctw": 24,
  "cwc": 1,
  "fstc": {
    "4": 1,
    "21": 1
  },
  "pcwc": 0,
  "rwsp": {
    "8": 10
  },
  "hashr": "2:8;10;5;10;7#8;10;9;5;5#7;8;5;6;8#6;7;0;8;10#8;10;9;4;10#7;10;9;9;7#3;4;5;6;8#R#8#010412233342#MV#0#MT#1#MG#24.0#",
  "fb": null,
  "sid": "1981349010102812160",
  "psid": "1981348960584859136",
  "st": 21,
  "nst": 22,
  "pf": 2,
  "aw": 31.2,
  "wid": 0,
  "wt": "C",
  "wk": "0_C",
  "wbn": null,
  "wfg": null,
  "blb": 136694.2,
  "blab": 136694.2,
  "bl": 136718.2,
  "tb": 0,
  "tbb": 12,
  "tw": 24,
  "np": 24,
  "ocr": null,
  "mr": null,
  "ge": [
    2,
    11
  ]
}