{
  "wp": {
    "7": [
      3,
      10,
      17,
      18,
      24
    ],
    "9": [
      1,
      10,
      17,
      18,
      24,
      30
    ],
    "10": [
      2,
      4,
      10,
      15,
      17,
      18,
      24,
      31,
      32
    ]
  },
  "lw": {
    "7": 6,
    "9": 7.2,
    "10": 43.2
  },
  "orl": [
    5,
    9,
    10,
    7,
    10,
    6,
    8,
    6,
    5,
    6,
    0,
    5,
    5,
    6,
    6,
    10,
    5,
    0,
    0,
    5,
    10,
    9,
    1,
    6,
    0,
    5,
    5,
    7,
    10,
    8,
    9,
    10,
    10,
    8,
    7
  ],
  "snww": {
    "7": 2,
    "9": 2,
    "10": 12
  },
  "ssb": {
    "2": 13,
    "4": 19,
    "9": 20,
    "12": 16,
    "14": 15,
    "15": 14,
    "16": 7
  },
  "ss": {
    "2": 13,
    "4": 19,
    "9": 20,
    "12": 16,
    "15": 14,
    "16": 7
  },
  "fs": {
    "aw": 1365.6,
    "s": 10,
    "ts": 12,
    "nosa": 0
  },
  "rs": {
    "sspt": {
      "4": {
        "op": 18,
        "np": 19
      },
      "12": {
        "op": 15,
        "np": 16
      },
      "14": {
        "op": 14,
        "np": 15
      }
    },
    "rns": [
      [
        5,
        9,
        10
      ],
      [
        6,
        5
      ],
      [
        6
      ],
      [
        9,
        1
      ],
      [
        10,
        8
      ]
    ],
    "rnss": [
      [],
      [
        0
      ],
      [
        0
      ],
      [],
      []
    ],
    "bsb": []
  },
  "ssaw": 1327.2,
  "ptbr": [
    3,
    10,
    17,
    18,
    24,
    1,
    30,
    2,
    4,
    31,
    32
  ],
  "sc": 1,
  "mi": 3,
  "wm": 10,
  "lwa": 56.4,
  "gwt": 4,
  "pmt": null,
  "ab": null,
  "ml": 2,
  "cs": 0.3,
  "rl": [
    5,
    9,
    10,
    7,
    10,
    6,
    8,
    6,
    5,
    6,
    0,
    5,
    5,
    6,
    6,
    0,
    5,
    0,
    0,
    5,
    10,
    9,
    1,
    6,
    0,
    5,
    5,
    7,
    10,
    8,
    9,
    10,
    10,
    8,
    7
  ],
  "ctw": 564,
  "cwc": 5,
  "fstc": {
    "4": 1,
    "21": 2,
    "22": 6
  },
  "pcwc": 0,
  "rwsp": {
    "7": 5,
    "9": 6,
    "10": 6
  },
  "hashr": "9:5;6;6;9;10#9;5;0;1;8#10;6;5;6;9#7;0;0;0;10#10;5;0;5;10#6;5;5;5;8#8;6;10;7;7#R#7#0313232433#MV#0#MT#1#R#9#011323243342#MV#0#MT#1#R#10#020413212324334344#MV#0#MT#1#MG#564.0#",
  "fb": null,
  "sid": "1981349119553175040",
  "psid": "1981348960584859136",
  "st": 22,
  "nst": 22,
  "pf": 2,
  "aw": 1372.8,
  "wid": 0,
  "wt": "C",
  "wk": "0_C",
  "wbn": null,
  "wfg": null,
  "blb": 137495.8,
  "blab": 137495.8,
  "bl": 138059.8,
  "tb": 0,
  "tbb": 12,
  "tw": 564,
  "np": 564,
  "ocr": null,
  "mr": null,
  "ge": [
    1,
    11
  ]
}