{
  "wp": {
    "6": [
      1,
      12,
      16,
      22
    ]
  },
  "lw": {
    "6": 3
  },
  "orl": [
    7,
    6,
    7,
    8,
    7,
    10,
    6,
    10,
    10,
    7,
    10,
    5,
    0,
    7,
    9,
    10,
    6,
    9,
    5,
    1,
    9,
    3,
    6,
    3,
    5,
    4,
    9,
    6,
    7,
    7,
    10,
    4,
    5,
    7,
    2
  ],
  "snww": {
    "6": 1
  },
  "ssb": null,
  "ss": null,
  "fs": null,
  "rs": {
    "sspt": {},
    "rns": [
      [
        7
      ],
      [],
      [
        9,
        10
      ],
      [
        3
      ],
      []
    ],
    "rnss": [
      [],
      [],
      [],
      [],
      []
    ],
    "bsb": []
  },
  "ssaw": 12,
  "ptbr": [
    1,
    12,
    16,
    22
  ],
  "sc": 1,
  "mi": 1,
  "wm": 2,
  "lwa": 3,
  "gwt": -1,
  "pmt": null,
  "ab": null,
  "ml": 2,
  "cs": 0.3,
  "rl": [
    7,
    6,
    7,
    8,
    7,
    10,
    6,
    10,
    10,
    7,
    10,
    5,
    0,
    7,
    9,
    10,
    6,
    9,
    5,
    1,
    9,
    3,
    6,
    3,
    5,
    4,
    9,
    6,
    7,
    7,
    10,
    4,
    5,
    7,
    2
  ],
  "ctw": 6,
  "cwc": 2,
  "fstc": {
    "4": 1
  },
  "pcwc": 0,
  "rwsp": {
    "6": 5
  },
  "hashr": "1:7;10;9;3;7#6;10;10;6;7#7;7;6;3;10#8;10;9;5;4#7;5;5;4;5#10;0;1;9;7#6;7;9;6;2#R#6#01152231#MV#0#MT#1#MG#6.0#",
  "fb": null,
  "sid": "1981258585186762240",
  "psid": "1981258569810443776",
  "st": 4,
  "nst": 4,
  "pf": 2,
  "aw": 12,
  "wid": 0,
  "wt": "C",
  "wk": "0_C",
  "wbn": null,
  "wfg": null,
  "blb": 116069.2,
  "blab": 116069.2,
  "bl": 116075.2,
  "tb": 0,
  "tbb": 12,
  "tw": 6,
  "np": 6,
  "ocr": null,
  "mr": null,
  "ge": [
    1,
    11
  ]
}