{
  "wp": {
    "5": [
      2,
      8,
      10,
      16
    ]
  },
  "lw": {
    "5": 6
  },
  "orl": [
    8,
    7,
    5,
    8,
    7,
    8,
    7,
    4,
    5,
    10,
    0,
    10,
    7,
    7,
    9,
    9,
    5,
    4,
    9,
    2,
    2,
    8,
    8,
    8,
    8,
    8,
    7,
    9,
    5,
    10,
    5,
    5,
    2,
    4,
    7
  ],
  "snww": {
    "5": 2
  },
  "ssb": {
    "1": 7,
    "3": 24,
    "4": 27,
    "5": 21
  },
  "ss": {
    "1": 7,
    "3": 24,
    "4": 27,
    "5": 21
  },
  "fs": null,
  "rs": {
    "sspt": {
      "3": {
        "op": 23,
        "np": 24
      }
    },
    "rns": [
      [
        8
      ],
      [],
      [
        9,
        9
      ],
      [
        8
      ],
      []
    ],
    "rnss": [
      [],
      [],
      [],
      [
        0
      ],
      []
    ],
    "bsb": []
  },
  "ssaw": 18,
  "ptbr": [
    2,
    8,
    10,
    16
  ],
  "sc": 0,
  "mi": 1,
  "wm": 2,
  "lwa": 6,
  "gwt": -1,
  "pmt": null,
  "ab": null,
  "ml": 2,
  "cs": 0.3,
  "rl": [
    8,
    7,
    5,
    8,
    7,
    8,
    7,
    4,
    5,
    10,
    0,
    10,
    7,
    7,
    9,
    9,
    5,
    4,
    9,
    2,
    2,
    8,
    8,
    8,
    8,
    8,
    7,
    9,
    5,
    10,
    5,
    5,
    2,
    4,
    7
  ],
  "ctw": 12,
  "cwc": 2,
  "fstc": {
    "4": 1
  },
  "pcwc": 0,
  "rwsp": {
    "5": 5
  },
  "hashr": "1:8;4;9;8;5#7;5;9;8;10#5;10;5;8;5#8;0;4;8;5#7;10;9;8;2#8;7;2;7;4#7;7;2;9;7#R#5#02111322#MV#0#MT#1#MG#12.0#",
  "fb": null,
  "sid": "1981166356535442944",
  "psid": "1981166341352062464",
  "st": 4,
  "nst": 4,
  "pf": 2,
  "aw": 18,
  "wid": 0,
  "wt": "C",
  "wk": "0_C",
  "wbn": null,
  "wfg": null,
  "blb": 124741,
  "blab": 124741,
  "bl": 124753,
  "tb": 0,
  "tbb": 12,
  "tw": 12,
  "np": 12,
  "ocr": null,
  "mr": null,
  "ge": [
    1,
    11
  ]
}