{
  "wp": {
    "4": [
      4,
      12,
      15
    ]
  },
  "lw": {
    "4": 3.6
  },
  "orl": [
    5,
    6,
    7,
    5,
    4,
    10,
    5,
    8,
    9,
    2,
    8,
    5,
    4,
    5,
    4,
    4,
    10,
    8,
    8,
    1,
    6,
    4,
    10,
    7,
    3,
    10,
    7,
    9,
    4,
    8,
    3,
    7,
    9,
    8,
    10
  ],
  "snww": {
    "4": 1
  },
  "ssb": {
    "1": 7
  },
  "ss": {
    "1": 7
  },
  "fs": null,
  "rs": {
    "sspt": {},
    "rns": [
      [
        5
      ],
      [
        8
      ],
      [
        4
      ],
      [],
      []
    ],
    "rnss": [
      [],
      [
        0
      ],
      [],
      [],
      []
    ],
    "bsb": []
  },
  "ssaw": 7.8,
  "ptbr": [
    4,
    12,
    15
  ],
  "sc": 1,
  "mi": 1,
  "wm": 2,
  "lwa": 3.6,
  "gwt": -1,
  "pmt": null,
  "ab": null,
  "ml": 2,
  "cs": 0.3,
  "rl": [
    5,
    6,
    7,
    5,
    4,
    10,
    5,
    8,
    9,
    2,
    8,
    5,
    4,
    5,
    4,
    4,
    10,
    8,
    8,
    1,
    6,
    4,
    10,
    7,
    3,
    10,
    7,
    9,
    4,
    8,
    3,
    7,
    9,
    8,
    10
  ],
  "ctw": 7.2,
  "cwc": 2,
  "fstc": {
    "4": 1
  },
  "pcwc": 0,
  "rwsp": {
    "4": 6
  },
  "hashr": "1:5;8;4;4;4#6;9;4;10;8#7;2;10;7;3#5;8;8;3;7#4;5;8;10;9#10;4;1;7;8#5;5;6;9;10#R#4#041521#MV#0#MT#1#MG#7.2#",
  "fb": null,
  "sid": "1981381025929887232",
  "psid": "1981381010884918784",
  "st": 4,
  "nst": 4,
  "pf": 2,
  "aw": 7.8,
  "wid": 0,
  "wt": "C",
  "wk": "0_C",
  "wbn": null,
  "wfg": null,
  "blb": 151985.2,
  "blab": 151985.2,
  "bl": 151992.4,
  "tb": 0,
  "tbb": 12,
  "tw": 7.2,
  "np": 7.2,
  "ocr": null,
  "mr": null,
  "ge": [
    1,
    11
  ]
}