{
  "wc": 16,
  "ist": false,
  "itw": true,
  "fws": 3,
  "wp": {
    "5": [
      2,
      4,
      6
    ]
  },
  "orl": [
    4,
    6,
    3,
    7,
    3,
    6,
    3,
    5,
    4
  ],
  "lw": {
    "5": 15
  },
  "irs": true,
  "gwt": -1,
  "pmt": null,
  "ab": null,
  "ml": 2,
  "cs": 0.3,
  "rl": [
    4,
    6,
    3,
    7,
    3,
    6,
    3,
    5,
    4
  ],
  "ctw": 0,
  "cwc": 0,
  "fstc": null,
  "pcwc": 0,
  "rwsp": {
    "5": 25
  },
  "hashr": "0:4;7;3#6;3;5#3;6;4#R#3#021120#MV#3.0#MT#1#MG#0#",
  "fb": null,
  "sid": "1981062308318674432",
  "psid": "1981062308318674432",
  "st": 1,
  "nst": 4,
  "pf": 2,
  "aw": 0,
  "wid": 0,
  "wt": "C",
  "wk": "0_C",
  "wbn": null,
  "wfg": null,
  "blb": 109323.4,
  "blab": 109320.4,
  "bl": 109320.4,
  "tb": 3,
  "tbb": 3,
  "tw": 0,
  "np": -3,
  "ocr": null,
  "mr": null,
  "ge": [
    4,
    11
  ]
}