{
  "wp": null,
  "lw": null,
  "orl": [
    10,
    7,
    8,
    8,
    8,
    8,
    7,
    6,
    5,
    5,
    4,
    10,
    4,
    7,
    6,
    5,
    3,
    1,
    3,
    2,
    7,
    9,
    8,
    10,
    3,
    10,
    3,
    9,
    6,
    5,
    7,
    5,
    7,
    7,
    10
  ],
  "snww": null,
  "ssb": {
    "4": 18,
    "7": 19,
    "8": 20,
    "9": 17,
    "10": 16,
    "11": 15,
    "12": 14
  },
  "ss": {
    "4": 18,
    "7": 19,
    "8": 20,
    "9": 17,
    "10": 16,
    "11": 15,
    "12": 14
  },
  "fs": {
    "aw": 372,
    "s": 0,
    "ts": 10,
    "nosa": 0
  },
  "rs": {
    "sspt": {
      "9": {
        "op": 16,
        "np": 17
      },
      "10": {
        "op": 15,
        "np": 16
      },
      "11": {
        "op": 14,
        "np": 15
      }
    },
    "rns": [
      [
        10,
        7,
        8
      ],
      [
        6
      ],
      [
        6
      ],
      [],
      []
    ],
    "rnss": [
      [],
      [],
      [
        0
      ],
      [],
      []
    ],
    "bsb": []
  },
  "ssaw": 307.2,
  "ptbr": null,
  "sc": 1,
  "mi": 3,
  "wm": 10,
  "lwa": 0,
  "gwt": -1,
  "pmt": null,
  "ab": null,
  "ml": 2,
  "cs": 0.3,
  "rl": [
    10,
    7,
    8,
    8,
    8,
    8,
    7,
    6,
    5,
    5,
    4,
    10,
    4,
    7,
    6,
    5,
    3,
    1,
    3,
    2,
    7,
    9,
    8,
    10,
    3,
    10,
    3,
    9,
    6,
    5,
    7,
    5,
    7,
    7,
    10
  ],
  "ctw": 0,
  "cwc": 0,
  "fstc": {
    "21": 10,
    "22": 7
  },
  "pcwc": 0,
  "rwsp": null,
  "hashr": "17:10;6;6;9;6#7;5;5;8;5#8;5;3;10;7#8;4;1;3;5#8;10;3;10;7#8;4;2;3;7#7;7;7;9;10#MV#0#MT#1#MG#0#",
  "fb": null,
  "sid": "1981399653043666432",
  "psid": "1981399413272083968",
  "st": 22,
  "nst": 1,
  "pf": 2,
  "aw": 372,
  "wid": 0,
  "wt": "C",
  "wk": "0_C",
  "wbn": null,
  "wfg": null,
  "blb": 158149,
  "blab": 158149,
  "bl": 158149,
  "tb": 0,
  "tbb": 12,
  "tw": 0,
  "np": 0,
  "ocr": null,
  "mr": null,
  "ge": [
    1,
    11
  ]
}