{
  "wp": null,
  "lw": null,
  "orl": [
    9,
    10,
    5,
    10,
    5,
    5,
    7,
    5,
    9,
    8,
    9,
    5,
    0,
    8,
    7,
    9,
    7,
    4,
    8,
    7,
    4,
    6,
    3,
    3,
    5,
    8,
    7,
    6,
    4,
    8,
    7,
    8,
    6,
    9,
    8
  ],
  "snww": null,
  "ssb": {
    "2": 15,
    "3": 16,
    "4": 17,
    "5": 18,
    "6": 19,
    "8": 20,
    "9": 21,
    "10": 14
  },
  "ss": {
    "2": 15,
    "3": 16,
    "4": 17,
    "5": 18,
    "6": 19,
    "8": 20,
    "9": 21,
    "10": 14
  },
  "fs": {
    "aw": 112.8,
    "s": 6,
    "ts": 10,
    "nosa": 0
  },
  "rs": {
    "sspt": {
      "2": {
        "op": 14,
        "np": 15
      },
      "3": {
        "op": 15,
        "np": 16
      },
      "4": {
        "op": 16,
        "np": 17
      },
      "5": {
        "op": 17,
        "np": 18
      },
      "6": {
        "op": 18,
        "np": 19
      }
    },
    "rns": [
      [
        9,
        10,
        5
      ],
      [
        5,
        9,
        8,
        9
      ],
      [
        7
      ],
      [],
      []
    ],
    "rnss": [
      [],
      [],
      [
        0
      ],
      [],
      []
    ],
    "bsb": []
  },
  "ssaw": 45.6,
  "ptbr": null,
  "sc": 0,
  "mi": 2,
  "wm": 6,
  "lwa": 0,
  "gwt": -1,
  "pmt": null,
  "ab": null,
  "ml": 2,
  "cs": 0.3,
  "rl": [
    9,
    10,
    5,
    10,
    5,
    5,
    7,
    5,
    9,
    8,
    9,
    5,
    0,
    8,
    7,
    9,
    7,
    4,
    8,
    7,
    4,
    6,
    3,
    3,
    5,
    8,
    7,
    6,
    4,
    8,
    7,
    8,
    6,
    9,
    8
  ],
  "ctw": 0,
  "cwc": 0,
  "fstc": {
    "4": 2,
    "21": 4,
    "22": 4
  },
  "pcwc": 0,
  "rwsp": null,
  "hashr": "10:9;5;7;6;4#10;9;9;3;8#5;8;7;3;7#10;9;4;5;8#5;5;8;8;6#5;0;7;7;9#7;8;4;6;8#MV#0#MT#1#MG#0#",
  "fb": null,
  "sid": "1981175009627864576",
  "psid": "1981174831504162304",
  "st": 22,
  "nst": 21,
  "pf": 2,
  "aw": 146.4,
  "wid": 0,
  "wt": "C",
  "wk": "0_C",
  "wbn": null,
  "wfg": null,
  "blb": 127246.6,
  "blab": 127246.6,
  "bl": 127246.6,
  "tb": 0,
  "tbb": 12,
  "tw": 0,
  "np": 0,
  "ocr": null,
  "mr": null,
  "ge": [
    1,
    11
  ]
}