{
  "wp": {
    "9": [
      3,
      10,
      17
    ]
  },
  "lw": {
    "9": 0.6
  },
  "orl": [
    9,
    5,
    10,
    9,
    5,
    7,
    5,
    6,
    8,
    6,
    9,
    4,
    6,
    2,
    6,
    8,
    7,
    0,
    4,
    8,
    10,
    7,
    7,
    8,
    2,
    7,
    5,
    2,
    9,
    8,
    9,
    6,
    8,
    10,
    9
  ],
  "snww": {
    "9": 1
  },
  "ssb": {
    "1": 9,
    "2": 14,
    "3": 15,
    "4": 16,
    "6": 18,
    "7": 19,
    "8": 20
  },
  "ss": {
    "1": 9,
    "2": 14,
    "3": 15,
    "4": 16,
    "6": 18,
    "7": 19,
    "8": 20
  },
  "fs": {
    "aw": 631.2,
    "s": 5,
    "ts": 10,
    "nosa": 0
  },
  "rs": {
    "sspt": {
      "1": {
        "op": 8,
        "np": 9
      }
    },
    "rns": [
      [
        9,
        5
      ],
      [
        6
      ],
      [],
      [
        7,
        7
      ],
      []
    ],
    "rnss": [
      [],
      [],
      [],
      [],
      []
    ],
    "bsb": []
  },
  "ssaw": 16.8,
  "ptbr": [
    3,
    10,
    17
  ],
  "sc": 0,
  "mi": 1,
  "wm": 4,
  "lwa": 0.6,
  "gwt": -1,
  "pmt": null,
  "ab": null,
  "ml": 2,
  "cs": 0.3,
  "rl": [
    9,
    5,
    10,
    9,
    5,
    7,
    5,
    6,
    8,
    6,
    9,
    4,
    6,
    2,
    6,
    8,
    7,
    0,
    4,
    8,
    10,
    7,
    7,
    8,
    2,
    7,
    5,
    2,
    9,
    8,
    9,
    6,
    8,
    10,
    9
  ],
  "ctw": 2.4,
  "cwc": 2,
  "fstc": {
    "4": 3,
    "21": 5,
    "22": 10
  },
  "pcwc": 0,
  "rwsp": {
    "9": 1
  },
  "hashr": "18:9;6;6;7;9#5;8;8;7;8#10;6;7;8;9#9;9;0;2;6#5;4;4;7;8#7;6;8;5;10#5;2;10;2;9#R#9#031323#MV#0#MT#1#MG#2.4#",
  "fb": null,
  "sid": "1981118702132657664",
  "psid": "1981118377476750848",
  "st": 22,
  "nst": 22,
  "pf": 2,
  "aw": 706.2,
  "wid": 0,
  "wt": "C",
  "wk": "0_C",
  "wbn": null,
  "wfg": null,
  "blb": 104771.8,
  "blab": 104771.8,
  "bl": 104774.2,
  "tb": 0,
  "tbb": 12,
  "tw": 2.4,
  "np": 2.4,
  "ocr": null,
  "mr": null,
  "ge": [
    1,
    11
  ]
}