{
  "wp": {
    "6": [
      4,
      9,
      15,
      16,
      17,
      19,
      23,
      29,
      32
    ]
  },
  "lw": {
    "6": 57.6
  },
  "orl": [
    4,
    3,
    8,
    7,
    6,
    8,
    7,
    4,
    1,
    6,
    3,
    5,
    4,
    9,
    6,
    6,
    6,
    6,
    2,
    6,
    1,
    6,
    7,
    6,
    9,
    3,
    8,
    9,
    9,
    6,
    7,
    1,
    6,
    9,
    3
  ],
  "snww": {
    "6": 8
  },
  "ssb": {
    "1": 7,
    "2": 13,
    "3": 17
  },
  "ss": {
    "1": 7,
    "2": 13
  },
  "fs": null,
  "rs": null,
  "ssaw": 57.6,
  "ptbr": [
    4,
    9,
    15,
    16,
    19,
    23,
    29,
    32
  ],
  "sc": 2,
  "mi": 0,
  "wm": 1,
  "lwa": 57.6,
  "gwt": 1,
  "pmt": null,
  "ab": null,
  "ml": 2,
  "cs": 0.3,
  "rl": [
    4,
    3,
    8,
    7,
    6,
    8,
    7,
    4,
    1,
    6,
    3,
    5,
    4,
    9,
    6,
    6,
    6,
    0,
    2,
    6,
    1,
    6,
    7,
    6,
    9,
    3,
    8,
    9,
    9,
    6,
    7,
    1,
    6,
    9,
    3
  ],
  "ctw": 57.6,
  "cwc": 1,
  "fstc": null,
  "pcwc": 1,
  "rwsp": {
    "6": 12
  },
  "hashr": "0:4;4;6;6;9#3;1;6;7;6#8;6;6;6;7#7;3;0;9;1#6;5;2;3;6#8;4;6;8;9#7;9;1;9;3#R#6#041221222325324144#MV#12.0#MT#1#MG#57.6#",
  "fb": null,
  "sid": "1981156943049260544",
  "psid": "1981156943049260544",
  "st": 1,
  "nst": 4,
  "pf": 2,
  "aw": 57.6,
  "wid": 0,
  "wt": "C",
  "wk": "0_C",
  "wbn": null,
  "wfg": null,
  "blb": 123335.2,
  "blab": 123323.2,
  "bl": 123380.8,
  "tb": 12,
  "tbb": 12,
  "tw": 57.6,
  "np": 45.6,
  "ocr": null,
  "mr": null,
  "ge": [
    1,
    11
  ]
}