{
  "wp": {
    "6": [
      1,
      8,
      17,
      18,
      23,
      29
    ],
    "8": [
      2,
      9,
      18,
      26
    ],
    "10": [
      3,
      11,
      18
    ]
  },
  "lw": {
    "6": 14.4,
    "8": 2.4,
    "10": 0.6
  },
  "orl": [
    8,
    6,
    8,
    10,
    2,
    7,
    10,
    5,
    6,
    8,
    4,
    10,
    5,
    10,
    10,
    5,
    1,
    6,
    0,
    5,
    9,
    6,
    9,
    6,
    9,
    3,
    8,
    9,
    7,
    6,
    10,
    4,
    5,
    7,
    2
  ],
  "snww": {
    "6": 2,
    "8": 1,
    "10": 1
  },
  "ssb": {
    "1": 9
  },
  "ss": null,
  "fs": null,
  "rs": {
    "sspt": {
      "1": {
        "op": 7,
        "np": 9
      }
    },
    "rns": [
      [
        8,
        6
      ],
      [
        5,
        6
      ],
      [],
      [
        6
      ],
      [
        7
      ]
    ],
    "rnss": [
      [],
      [],
      [],
      [],
      []
    ],
    "bsb": []
  },
  "ssaw": 63.6,
  "ptbr": [
    1,
    8,
    17,
    18,
    23,
    29,
    2,
    26,
    3,
    11
  ],
  "sc": 1,
  "mi": 1,
  "wm": 2,
  "lwa": 17.4,
  "gwt": -1,
  "pmt": null,
  "ab": null,
  "ml": 2,
  "cs": 0.3,
  "rl": [
    8,
    6,
    8,
    10,
    2,
    7,
    10,
    5,
    6,
    0,
    4,
    10,
    5,
    10,
    10,
    5,
    1,
    6,
    0,
    5,
    9,
    6,
    9,
    6,
    9,
    3,
    8,
    9,
    7,
    6,
    10,
    4,
    5,
    7,
    2
  ],
  "ctw": 34.8,
  "cwc": 2,
  "fstc": {
    "4": 1
  },
  "pcwc": 0,
  "rwsp": {
    "6": 12,
    "8": 4,
    "10": 1
  },
  "hashr": "1:8;5;10;6;7#6;6;5;9;6#8;0;1;6;10#10;4;6;9;4#2;10;0;3;5#7;5;5;8;7#10;10;9;9;2#R#6#011123243241#MV#0#MT#1#R#8#02122435#MV#0#MT#1#R#10#031424#MV#0#MT#1#MG#34.8#",
  "fb": null,
  "sid": "1981391579717303808",
  "psid": "1981391564101910016",
  "st": 4,
  "nst": 4,
  "pf": 2,
  "aw": 63.6,
  "wid": 0,
  "wt": "C",
  "wk": "0_C",
  "wbn": null,
  "wfg": null,
  "blb": 153779.2,
  "blab": 153779.2,
  "bl": 153814,
  "tb": 0,
  "tbb": 12,
  "tw": 34.8,
  "np": 34.8,
  "ocr": null,
  "mr": null,
  "ge": [
    1,
    11
  ]
}