{
  "wp": {
    "10": [
      1,
      12,
      15
    ]
  },
  "lw": {
    "10": 0.6
  },
  "orl": [
    3,
    10,
    9,
    5,
    5,
    9,
    5,
    6,
    6,
    2,
    3,
    6,
    0,
    3,
    3,
    10,
    7,
    8,
    6,
    8,
    10,
    10,
    7,
    8,
    5,
    6,
    5,
    10,
    3,
    6,
    8,
    9,
    6,
    4,
    6
  ],
  "snww": {
    "10": 1
  },
  "ssb": {
    "1": 11,
    "3": 16,
    "5": 17,
    "6": 18,
    "7": 19,
    "9": 20,
    "10": 23,
    "11": 15,
    "12": 14
  },
  "ss": {
    "1": 11,
    "3": 16,
    "5": 17,
    "6": 18,
    "7": 19,
    "9": 20,
    "10": 23,
    "12": 14
  },
  "fs": {
    "aw": 451.2,
    "s": 3,
    "ts": 10,
    "nosa": 0
  },
  "rs": {
    "sspt": {
      "3": {
        "op": 14,
        "np": 16
      },
      "5": {
        "op": 16,
        "np": 17
      },
      "6": {
        "op": 17,
        "np": 18
      },
      "7": {
        "op": 18,
        "np": 19
      },
      "10": {
        "op": 22,
        "np": 23
      }
    },
    "rns": [
      [
        3,
        10,
        9
      ],
      [
        6
      ],
      [
        3,
        10
      ],
      [
        10
      ],
      []
    ],
    "rnss": [
      [],
      [],
      [
        1,
        0
      ],
      [],
      []
    ],
    "bsb": []
  },
  "ssaw": 61.2,
  "ptbr": [
    1,
    12
  ],
  "sc": 0,
  "mi": 2,
  "wm": 6,
  "lwa": 0.6,
  "gwt": -1,
  "pmt": null,
  "ab": null,
  "ml": 2,
  "cs": 0.3,
  "rl": [
    3,
    10,
    9,
    5,
    5,
    9,
    5,
    6,
    6,
    2,
    3,
    6,
    0,
    3,
    3,
    0,
    7,
    8,
    6,
    8,
    10,
    10,
    7,
    8,
    5,
    6,
    5,
    10,
    3,
    6,
    8,
    9,
    6,
    4,
    6
  ],
  "ctw": 3.6,
  "cwc": 3,
  "fstc": {
    "4": 1,
    "21": 7,
    "22": 7
  },
  "pcwc": 0,
  "rwsp": {
    "10": 1
  },
  "hashr": "15:3;6;3;10;3#10;6;0;7;6#9;2;7;8;8#5;3;8;5;9#5;6;6;6;6#9;0;8;5;4#5;3;10;10;6#R#10#011521#MV#0#MT#1#MG#3.6#",
  "fb": null,
  "sid": "1981182880310623744",
  "psid": "1981182614924426752",
  "st": 22,
  "nst": 22,
  "pf": 2,
  "aw": 451.8,
  "wid": 0,
  "wt": "C",
  "wk": "0_C",
  "wbn": null,
  "wfg": null,
  "blb": 129619,
  "blab": 129619,
  "bl": 129622.6,
  "tb": 0,
  "tbb": 12,
  "tw": 3.6,
  "np": 3.6,
  "ocr": null,
  "mr": null,
  "ge": [
    1,
    11
  ]
}