{
  "wp": {
    "6": [
      1,
      10,
      15,
      25
    ]
  },
  "lw": {
    "6": 3
  },
  "orl": [
    3,
    6,
    7,
    8,
    1,
    10,
    7,
    7,
    8,
    7,
    0,
    5,
    3,
    4,
    9,
    6,
    9,
    10,
    5,
    9,
    9,
    4,
    9,
    8,
    7,
    6,
    7,
    9,
    4,
    4,
    2,
    5,
    10,
    7,
    2
  ],
  "snww": {
    "6": 1
  },
  "ssb": {
    "2": 15,
    "3": 9
  },
  "ss": {
    "3": 9
  },
  "fs": null,
  "rs": {
    "sspt": {
      "2": {
        "op": 14,
        "np": 15
      },
      "3": {
        "op": 8,
        "np": 9
      }
    },
    "rns": [
      [
        3,
        6,
        7
      ],
      [
        7
      ],
      [
        9
      ],
      [
        4,
        9,
        8,
        7
      ],
      []
    ],
    "rnss": [
      [],
      [],
      [],
      [],
      []
    ],
    "bsb": []
  },
  "ssaw": 48.6,
  "ptbr": [
    1,
    10,
    25
  ],
  "sc": 1,
  "mi": 2,
  "wm": 3,
  "lwa": 3,
  "gwt": -1,
  "pmt": null,
  "ab": null,
  "ml": 2,
  "cs": 0.3,
  "rl": [
    3,
    6,
    7,
    8,
    1,
    10,
    7,
    7,
    8,
    7,
    0,
    5,
    3,
    4,
    9,
    0,
    9,
    10,
    5,
    9,
    9,
    4,
    9,
    8,
    7,
    6,
    7,
    9,
    4,
    4,
    2,
    5,
    10,
    7,
    2
  ],
  "ctw": 9,
  "cwc": 3,
  "fstc": {
    "4": 2
  },
  "pcwc": 0,
  "rwsp": {
    "6": 5
  },
  "hashr": "2:3;7;9;4;4#6;8;0;9;4#7;7;9;8;2#8;0;10;7;5#1;5;5;6;10#10;3;9;7;7#7;4;9;9;2#R#6#01132134#MV#0#MT#1#MG#9.0#",
  "fb": null,
  "sid": "1981358008881380864",
  "psid": "1981357983027691008",
  "st": 4,
  "nst": 4,
  "pf": 2,
  "aw": 48.6,
  "wid": 0,
  "wt": "C",
  "wk": "0_C",
  "wbn": null,
  "wfg": null,
  "blb": 146366.2,
  "blab": 146366.2,
  "bl": 146375.2,
  "tb": 0,
  "tbb": 12,
  "tw": 9,
  "np": 9,
  "ocr": null,
  "mr": null,
  "ge": [
    1,
    11
  ]
}