{
  "wp": null,
  "lw": null,
  "orl": [
    9,
    4,
    5,
    10,
    5,
    9,
    8,
    9,
    9,
    6,
    8,
    9,
    1,
    6,
    10,
    10,
    4,
    4,
    7,
    10,
    7,
    5,
    6,
    7,
    6,
    5,
    2,
    10,
    9,
    6,
    7,
    3,
    9,
    8,
    3
  ],
  "snww": null,
  "ssb": null,
  "ss": null,
  "fs": null,
  "rs": null,
  "ssaw": 0,
  "ptbr": null,
  "sc": 1,
  "mi": 0,
  "wm": 1,
  "lwa": 0,
  "gwt": -1,
  "pmt": null,
  "ab": null,
  "ml": 2,
  "cs": 0.3,
  "rl": [
    9,
    4,
    5,
    10,
    5,
    9,
    8,
    9,
    9,
    6,
    8,
    9,
    1,
    6,
    10,
    10,
    4,
    4,
    7,
    10,
    7,
    5,
    6,
    7,
    6,
    5,
    2,
    10,
    9,
    6,
    7,
    3,
    9,
    8,
    3
  ],
  "ctw": 0,
  "cwc": 0,
  "fstc": null,
  "pcwc": 0,
  "rwsp": null,
  "hashr": "0:9;9;10;5;9#4;9;10;6;6#5;6;4;7;7#10;8;4;6;3#5;9;7;5;9#9;1;10;2;8#8;6;7;10;3#MV#12.0#MT#1#MG#0#",
  "fb": null,
  "sid": "1981357032166391296",
  "psid": "1981357032166391296",
  "st": 1,
  "nst": 1,
  "pf": 2,
  "aw": 0,
  "wid": 0,
  "wt": "C",
  "wk": "0_C",
  "wbn": null,
  "wfg": null,
  "blb": 145753.6,
  "blab": 145741.6,
  "bl": 145741.6,
  "tb": 12,
  "tbb": 12,
  "tw": 0,
  "np": -12,
  "ocr": null,
  "mr": null,
  "ge": [
    1,
    11
  ]
}