{
  "wp": {
    "5": [
      3,
      10,
      11,
      12,
      17
    ],
    "7": [
      2,
      4,
      9,
      11,
      17
    ],
    "9": [
      1,
      11,
      17,
      18,
      23,
      25,
      26
    ]
  },
  "lw": {
    "5": 9,
    "7": 7.2,
    "9": 10.8
  },
  "orl": [
    7,
    9,
    7,
    5,
    7,
    9,
    4,
    5,
    10,
    7,
    5,
    0,
    5,
    2,
    9,
    6,
    2,
    0,
    9,
    6,
    5,
    8,
    3,
    9,
    8,
    9,
    9,
    3,
    6,
    5,
    5,
    6,
    1,
    6,
    9
  ],
  "snww": {
    "5": 3,
    "7": 4,
    "9": 6
  },
  "ssb": {
    "3": 16,
    "4": 14,
    "5": 21
  },
  "ss": {
    "3": 16,
    "4": 14,
    "5": 21
  },
  "fs": null,
  "rs": {
    "sspt": {
      "3": {
        "op": 14,
        "np": 16
      }
    },
    "rns": [
      [
        7,
        9,
        7,
        5
      ],
      [
        5,
        10,
        7
      ],
      [
        9,
        6
      ],
      [
        8,
        3,
        9
      ],
      [
        6,
        5
      ]
    ],
    "rnss": [
      [],
      [],
      [
        0
      ],
      [
        0
      ],
      []
    ],
    "bsb": []
  },
  "ssaw": 465,
  "ptbr": [
    3,
    10,
    11,
    12,
    17,
    2,
    4,
    9,
    1,
    18,
    23,
    25,
    26
  ],
  "sc": 1,
  "mi": 2,
  "wm": 3,
  "lwa": 27,
  "gwt": 2,
  "pmt": null,
  "ab": null,
  "ml": 2,
  "cs": 0.3,
  "rl": [
    7,
    9,
    7,
    5,
    7,
    9,
    4,
    5,
    10,
    7,
    5,
    0,
    5,
    2,
    9,
    6,
    2,
    0,
    9,
    6,
    5,
    8,
    3,
    9,
    8,
    9,
    9,
    3,
    6,
    5,
    5,
    6,
    1,
    6,
    9
  ],
  "ctw": 81,
  "cwc": 3,
  "fstc": {
    "4": 2
  },
  "pcwc": 0,
  "rwsp": {
    "5": 5,
    "7": 3,
    "9": 3
  },
  "hashr": "2:7;5;9;8;6#9;10;6;3;5#7;7;2;9;5#5;5;0;8;6#7;0;9;9;1#9;5;6;9;6#4;2;5;3;9#R#5#0313141523#MV#0#MT#1#R#7#0204121423#MV#0#MT#1#R#9#01142324323435#MV#0#MT#1#MG#81.0#",
  "fb": null,
  "sid": "1981399018223173120",
  "psid": "1981398991237021184",
  "st": 4,
  "nst": 4,
  "pf": 2,
  "aw": 465,
  "wid": 0,
  "wt": "C",
  "wk": "0_C",
  "wbn": null,
  "wfg": null,
  "blb": 157763.8,
  "blab": 157763.8,
  "bl": 157844.8,
  "tb": 0,
  "tbb": 12,
  "tw": 81,
  "np": 81,
  "ocr": null,
  "mr": null,
  "ge": [
    1,
    11
  ]
}