{
  "wp": null,
  "lw": null,
  "orl": [
    7,
    8,
    7,
    6,
    7,
    4,
    1,
    5,
    4,
    7,
    10,
    8,
    2,
    10,
    2,
    9,
    5,
    6,
    6,
    2,
    6,
    5,
    8,
    6,
    1,
    6,
    8,
    8,
    9,
    2,
    4,
    7,
    5,
    7,
    8
  ],
  "snww": null,
  "ssb": {
    "1": 9,
    "2": 16,
    "3": 25
  },
  "ss": {
    "1": 9,
    "2": 16,
    "3": 25
  },
  "fs": null,
  "rs": {
    "sspt": {
      "2": {
        "op": 15,
        "np": 16
      },
      "3": {
        "op": 24,
        "np": 25
      }
    },
    "rns": [
      [
        7
      ],
      [
        5
      ],
      [
        2
      ],
      [
        5,
        8
      ],
      [
        9
      ]
    ],
    "rnss": [
      [],
      [],
      [],
      [],
      []
    ],
    "bsb": []
  },
  "ssaw": 7.2,
  "ptbr": null,
  "sc": 1,
  "mi": 1,
  "wm": 2,
  "lwa": 0,
  "gwt": -1,
  "pmt": null,
  "ab": null,
  "ml": 2,
  "cs": 0.3,
  "rl": [
    7,
    8,
    7,
    6,
    7,
    4,
    1,
    5,
    4,
    7,
    10,
    8,
    2,
    10,
    2,
    9,
    5,
    6,
    6,
    2,
    6,
    5,
    8,
    6,
    1,
    6,
    8,
    8,
    9,
    2,
    4,
    7,
    5,
    7,
    8
  ],
  "ctw": 0,
  "cwc": 0,
  "fstc": {
    "4": 1
  },
  "pcwc": 0,
  "rwsp": null,
  "hashr": "1:7;5;2;5;9#8;4;9;8;2#7;7;5;6;4#6;10;6;1;7#7;8;6;6;5#4;2;2;8;7#1;10;6;8;8#MV#0#MT#1#MG#0#",
  "fb": null,
  "sid": "1981258290738232832",
  "psid": "1981258275156393472",
  "st": 4,
  "nst": 1,
  "pf": 2,
  "aw": 7.2,
  "wid": 0,
  "wt": "C",
  "wk": "0_C",
  "wbn": null,
  "wfg": null,
  "blb": 116161,
  "blab": 116161,
  "bl": 116161,
  "tb": 0,
  "tbb": 12,
  "tw": 0,
  "np": 0,
  "ocr": null,
  "mr": null,
  "ge": [
    1,
    11
  ]
}