{
  "wp": {
    "8": [
      1,
      11,
      12,
      16
    ]
  },
  "lw": {
    "8": 2.4
  },
  "orl": [
    4,
    8,
    9,
    5,
    5,
    8,
    10,
    3,
    9,
    9,
    6,
    8,
    8,
    6,
    10,
    4,
    8,
    4,
    7,
    7,
    10,
    7,
    7,
    7,
    3,
    7,
    2,
    6,
    6,
    5,
    6,
    8,
    9,
    10,
    8
  ],
  "snww": {
    "8": 2
  },
  "ssb": {
    "1": 9,
    "2": 11,
    "4": 16,
    "5": 24,
    "6": 27,
    "7": 7,
    "8": 21
  },
  "ss": {
    "1": 9,
    "5": 24,
    "6": 27,
    "7": 7,
    "8": 21
  },
  "fs": null,
  "rs": {
    "sspt": {
      "1": {
        "op": 8,
        "np": 9
      },
      "2": {
        "op": 10,
        "np": 11
      },
      "5": {
        "op": 22,
        "np": 24
      }
    },
    "rns": [
      [
        4,
        8
      ],
      [
        3
      ],
      [
        10
      ],
      [
        7,
        7
      ],
      []
    ],
    "rnss": [
      [],
      [
        0
      ],
      [],
      [
        0
      ],
      []
    ],
    "bsb": []
  },
  "ssaw": 22.8,
  "ptbr": [
    1,
    12
  ],
  "sc": 0,
  "mi": 2,
  "wm": 3,
  "lwa": 2.4,
  "gwt": -1,
  "pmt": null,
  "ab": null,
  "ml": 2,
  "cs": 0.3,
  "rl": [
    4,
    8,
    9,
    5,
    5,
    8,
    10,
    3,
    9,
    9,
    6,
    0,
    8,
    6,
    10,
    4,
    0,
    4,
    7,
    7,
    10,
    7,
    7,
    7,
    3,
    7,
    2,
    6,
    6,
    5,
    6,
    8,
    9,
    10,
    8
  ],
  "ctw": 7.2,
  "cwc": 3,
  "fstc": {
    "4": 2
  },
  "pcwc": 0,
  "rwsp": {
    "8": 2
  },
  "hashr": "2:4;3;10;7;6#8;9;4;7;5#9;9;0;7;6#5;6;4;3;8#5;0;7;7;9#8;8;7;2;10#10;6;10;6;8#R#8#01141522#MV#0#MT#1#MG#7.2#",
  "fb": null,
  "sid": "1981258973927439872",
  "psid": "1981258950397394432",
  "st": 4,
  "nst": 4,
  "pf": 2,
  "aw": 22.8,
  "wid": 0,
  "wt": "C",
  "wk": "0_C",
  "wbn": null,
  "wfg": null,
  "blb": 115915,
  "blab": 115915,
  "bl": 115922.2,
  "tb": 0,
  "tbb": 12,
  "tw": 7.2,
  "np": 7.2,
  "ocr": null,
  "mr": null,
  "ge": [
    1,
    11
  ]
}