{
  "wp": {
    "8": [
      3,
      10,
      18,
      19,
      24,
      26,
      29
    ]
  },
  "lw": {
    "8": 24
  },
  "orl": [
    6,
    3,
    7,
    8,
    6,
    7,
    2,
    10,
    7,
    10,
    8,
    4,
    5,
    5,
    6,
    9,
    5,
    5,
    8,
    8,
    5,
    8,
    6,
    9,
    8,
    4,
    0,
    2,
    8,
    8,
    10,
    5,
    4,
    2,
    5
  ],
  "snww": {
    "8": 4
  },
  "ssb": {
    "2": 24,
    "3": 25
  },
  "ss": {
    "3": 25
  },
  "fs": null,
  "rs": {
    "sspt": {},
    "rns": [
      [
        6,
        3
      ],
      [
        10,
        7,
        10
      ],
      [
        6
      ],
      [],
      [
        8
      ]
    ],
    "rnss": [
      [],
      [],
      [],
      [],
      []
    ],
    "bsb": []
  },
  "ssaw": 105.6,
  "ptbr": [
    3,
    10,
    18,
    19,
    26,
    29
  ],
  "sc": 0,
  "mi": 2,
  "wm": 3,
  "lwa": 24,
  "gwt": 2,
  "pmt": null,
  "ab": null,
  "ml": 2,
  "cs": 0.3,
  "rl": [
    6,
    3,
    7,
    8,
    6,
    7,
    2,
    10,
    7,
    10,
    8,
    4,
    5,
    5,
    6,
    9,
    5,
    5,
    8,
    8,
    5,
    8,
    6,
    9,
    0,
    4,
    0,
    2,
    8,
    8,
    10,
    5,
    4,
    2,
    5
  ],
  "ctw": 72,
  "cwc": 3,
  "fstc": {
    "4": 2
  },
  "pcwc": 0,
  "rwsp": {
    "8": 10
  },
  "hashr": "2:6;10;6;8;8#3;7;9;6;8#7;10;5;9;10#8;8;5;0;5#6;4;8;4;4#7;5;8;0;2#2;5;5;2;5#R#8#03132425333541#MV#0#MT#1#MG#72.0#",
  "fb": null,
  "sid": "1981179831106141696",
  "psid": "1981179807009865216",
  "st": 4,
  "nst": 4,
  "pf": 2,
  "aw": 105.6,
  "wid": 0,
  "wt": "C",
  "wk": "0_C",
  "wbn": null,
  "wfg": null,
  "blb": 129065.8,
  "blab": 129065.8,
  "bl": 129137.8,
  "tb": 0,
  "tbb": 12,
  "tw": 72,
  "np": 72,
  "ocr": null,
  "mr": null,
  "ge": [
    1,
    11
  ]
}