{
  "wp": null,
  "lw": null,
  "orl": [
    8,
    7,
    7,
    7,
    3,
    8,
    7,
    10,
    10,
    9,
    5,
    7,
    5,
    4,
    5,
    6,
    10,
    2,
    2,
    5,
    5,
    6,
    9,
    5,
    8,
    9,
    8,
    8,
    8,
    5,
    1,
    4,
    10,
    5,
    4
  ],
  "snww": null,
  "ssb": {
    "1": 10,
    "2": 11,
    "3": 17,
    "4": 23
  },
  "ss": {
    "1": 10,
    "2": 11,
    "3": 17,
    "4": 23
  },
  "fs": null,
  "rs": {
    "sspt": {
      "1": {
        "op": 9,
        "np": 10
      },
      "4": {
        "op": 21,
        "np": 23
      }
    },
    "rns": [
      [
        8
      ],
      [
        10
      ],
      [
        5
      ],
      [
        6,
        9
      ],
      []
    ],
    "rnss": [
      [],
      [],
      [],
      [],
      []
    ],
    "bsb": []
  },
  "ssaw": 6,
  "ptbr": null,
  "sc": 1,
  "mi": 1,
  "wm": 2,
  "lwa": 0,
  "gwt": -1,
  "pmt": null,
  "ab": null,
  "ml": 2,
  "cs": 0.3,
  "rl": [
    8,
    7,
    7,
    7,
    3,
    8,
    7,
    10,
    10,
    9,
    5,
    7,
    5,
    4,
    5,
    6,
    10,
    2,
    2,
    5,
    5,
    6,
    9,
    5,
    8,
    9,
    8,
    8,
    8,
    5,
    1,
    4,
    10,
    5,
    4
  ],
  "ctw": 0,
  "cwc": 0,
  "fstc": {
    "4": 1
  },
  "pcwc": 0,
  "rwsp": null,
  "hashr": "1:8;10;5;6;8#7;10;6;9;5#7;9;10;5;1#7;5;2;8;4#3;7;2;9;10#8;5;5;8;5#7;4;5;8;4#MV#0#MT#1#MG#0#",
  "fb": null,
  "sid": "1981283709218717184",
  "psid": "1981283697566940672",
  "st": 4,
  "nst": 1,
  "pf": 2,
  "aw": 6,
  "wid": 0,
  "wt": "C",
  "wk": "0_C",
  "wbn": null,
  "wfg": null,
  "blb": 120862.6,
  "blab": 120862.6,
  "bl": 120862.6,
  "tb": 0,
  "tbb": 12,
  "tw": 0,
  "np": 0,
  "ocr": null,
  "mr": null,
  "ge": [
    1,
    11
  ]
}