{
  "wp": {
    "8": [
      2,
      10,
      12,
      16
    ]
  },
  "lw": {
    "8": 2.4
  },
  "orl": [
    10,
    10,
    8,
    10,
    5,
    9,
    10,
    3,
    6,
    6,
    8,
    6,
    8,
    9,
    10,
    10,
    0,
    4,
    7,
    7,
    10,
    6,
    2,
    10,
    10,
    10,
    6,
    1,
    9,
    6,
    9,
    7,
    8,
    5,
    6
  ],
  "snww": {
    "8": 2
  },
  "ssb": {
    "1": 10
  },
  "ss": null,
  "fs": null,
  "rs": {
    "sspt": {},
    "rns": [
      [
        10,
        10
      ],
      [
        3
      ],
      [
        10
      ],
      [],
      []
    ],
    "rnss": [
      [],
      [],
      [],
      [],
      []
    ],
    "bsb": []
  },
  "ssaw": 36,
  "ptbr": [
    2,
    12,
    16
  ],
  "sc": 0,
  "mi": 2,
  "wm": 3,
  "lwa": 2.4,
  "gwt": -1,
  "pmt": null,
  "ab": null,
  "ml": 2,
  "cs": 0.3,
  "rl": [
    10,
    10,
    8,
    10,
    5,
    9,
    10,
    3,
    6,
    6,
    0,
    6,
    8,
    9,
    10,
    10,
    0,
    4,
    7,
    7,
    10,
    6,
    2,
    10,
    10,
    10,
    6,
    1,
    9,
    6,
    9,
    7,
    8,
    5,
    6
  ],
  "ctw": 7.2,
  "cwc": 3,
  "fstc": {
    "4": 2
  },
  "pcwc": 0,
  "rwsp": {
    "8": 2
  },
  "hashr": "2:10;3;10;6;9#10;6;10;2;6#8;6;0;10;9#10;0;4;10;7#5;6;7;10;8#9;8;7;6;5#10;9;10;1;6#R#8#02131522#MV#0#MT#1#MG#7.2#",
  "fb": null,
  "sid": "1981394905565494784",
  "psid": "1981394879955074560",
  "st": 4,
  "nst": 4,
  "pf": 2,
  "aw": 36,
  "wid": 0,
  "wt": "C",
  "wk": "0_C",
  "wbn": null,
  "wfg": null,
  "blb": 158011.6,
  "blab": 158011.6,
  "bl": 158018.8,
  "tb": 0,
  "tbb": 12,
  "tw": 7.2,
  "np": 7.2,
  "ocr": null,
  "mr": null,
  "ge": [
    1,
    11
  ]
}