{
  "wp": {
    "6": [
      3,
      12,
      15,
      16,
      23
    ],
    "8": [
      1,
      2,
      10,
      19,
      22
    ]
  },
  "lw": {
    "6": 6,
    "8": 4.8
  },
  "orl": [
    7,
    8,
    8,
    6,
    7,
    4,
    6,
    5,
    5,
    10,
    8,
    5,
    6,
    8,
    10,
    6,
    6,
    9,
    9,
    8,
    10,
    10,
    8,
    6,
    9,
    7,
    3,
    9,
    10,
    10,
    7,
    5,
    7,
    10,
    2
  ],
  "snww": {
    "6": 2,
    "8": 2
  },
  "ssb": {
    "1": 10,
    "2": 13,
    "3": 25
  },
  "ss": {
    "2": 13,
    "3": 25
  },
  "fs": null,
  "rs": null,
  "ssaw": 10.8,
  "ptbr": [
    3,
    12,
    15,
    16,
    23,
    1,
    2,
    19,
    22
  ],
  "sc": 0,
  "mi": 0,
  "wm": 1,
  "lwa": 10.8,
  "gwt": -1,
  "pmt": null,
  "ab": null,
  "ml": 2,
  "cs": 0.3,
  "rl": [
    7,
    8,
    8,
    6,
    7,
    4,
    6,
    5,
    5,
    10,
    0,
    5,
    6,
    8,
    10,
    6,
    6,
    9,
    9,
    8,
    10,
    10,
    8,
    6,
    9,
    7,
    3,
    9,
    10,
    10,
    7,
    5,
    7,
    10,
    2
  ],
  "ctw": 10.8,
  "cwc": 1,
  "fstc": null,
  "pcwc": 1,
  "rwsp": {
    "6": 5,
    "8": 4
  },
  "hashr": "0:7;5;10;10;10#8;5;6;8;10#8;10;6;6;7#6;0;9;9;5#7;5;9;7;7#4;6;8;3;10#6;8;10;9;2#R#6#0315212232#MV#12.0#MT#1#R#8#0102132531#MV#12.0#MT#1#MG#10.8#",
  "fb": null,
  "sid": "1981144642229370368",
  "psid": "1981144642229370368",
  "st": 1,
  "nst": 4,
  "pf": 2,
  "aw": 10.8,
  "wid": 0,
  "wt": "C",
  "wk": "0_C",
  "wbn": null,
  "wfg": null,
  "blb": 117587.2,
  "blab": 117575.2,
  "bl": 117586,
  "tb": 12,
  "tbb": 12,
  "tw": 10.8,
  "np": -1.2,
  "ocr": null,
  "mr": null,
  "ge": [
    1,
    11
  ]
}