{
  "wp": {
    "8": [
      1,
      10,
      17,
      19
    ],
    "9": [
      3,
      4,
      11,
      12,
      17,
      19
    ]
  },
  "lw": {
    "8": 2.4,
    "9": 4.8
  },
  "orl": [
    2,
    8,
    5,
    9,
    9,
    9,
    10,
    6,
    2,
    6,
    8,
    9,
    9,
    9,
    7,
    5,
    10,
    0,
    4,
    0,
    10,
    7,
    10,
    5,
    10,
    6,
    2,
    5,
    8,
    6,
    8,
    9,
    8,
    10,
    6
  ],
  "snww": {
    "8": 2,
    "9": 8
  },
  "ssb": {
    "3": 25,
    "4": 8,
    "5": 14
  },
  "ss": {
    "3": 25,
    "4": 8,
    "5": 14
  },
  "fs": null,
  "rs": {
    "sspt": {
      "3": {
        "op": 24,
        "np": 25
      },
      "4": {
        "op": 7,
        "np": 8
      }
    },
    "rns": [
      [
        2
      ],
      [
        6
      ],
      [
        7,
        5
      ],
      [
        7,
        10
      ],
      []
    ],
    "rnss": [
      [],
      [],
      [
        0
      ],
      [],
      []
    ],
    "bsb": []
  },
  "ssaw": 75,
  "ptbr": [
    1,
    10,
    17,
    19,
    3,
    4,
    11,
    12
  ],
  "sc": 0,
  "mi": 2,
  "wm": 3,
  "lwa": 7.2,
  "gwt": -1,
  "pmt": null,
  "ab": null,
  "ml": 2,
  "cs": 0.3,
  "rl": [
    2,
    8,
    5,
    9,
    9,
    9,
    10,
    6,
    2,
    6,
    8,
    9,
    9,
    9,
    7,
    5,
    10,
    0,
    4,
    0,
    10,
    7,
    10,
    5,
    10,
    6,
    2,
    5,
    8,
    6,
    8,
    9,
    8,
    10,
    6
  ],
  "ctw": 21.6,
  "cwc": 3,
  "fstc": {
    "4": 2
  },
  "pcwc": 0,
  "rwsp": {
    "8": 2,
    "9": 1
  },
  "hashr": "2:2;6;7;7;8#8;2;5;10;6#5;6;10;5;8#9;8;0;10;9#9;9;4;6;8#9;9;0;2;10#10;9;10;5;6#R#8#01132325#MV#0#MT#1#R#9#030414152325#MV#0#MT#1#MG#21.6#",
  "fb": null,
  "sid": "1981301232026779136",
  "psid": "1981301205879488000",
  "st": 4,
  "nst": 4,
  "pf": 2,
  "aw": 75,
  "wid": 0,
  "wt": "C",
  "wk": "0_C",
  "wbn": null,
  "wfg": null,
  "blb": 128102.8,
  "blab": 128102.8,
  "bl": 128124.4,
  "tb": 0,
  "tbb": 12,
  "tw": 21.6,
  "np": 21.6,
  "ocr": null,
  "mr": null,
  "ge": [
    1,
    11
  ]
}