{
  "wp": {
    "4": [
      2,
      9,
      15
    ],
    "5": [
      3,
      4,
      10,
      18,
      22,
      25
    ]
  },
  "lw": {
    "4": 3.6,
    "5": 24
  },
  "orl": [
    9,
    10,
    4,
    5,
    5,
    9,
    5,
    8,
    3,
    4,
    5,
    6,
    8,
    2,
    8,
    4,
    10,
    8,
    5,
    8,
    6,
    2,
    5,
    2,
    10,
    5,
    2,
    5,
    6,
    4,
    9,
    10,
    8,
    6,
    9
  ],
  "snww": {
    "4": 1,
    "5": 4
  },
  "ssb": {
    "1": 14,
    "2": 23,
    "3": 27
  },
  "ss": {
    "1": 14,
    "2": 23,
    "3": 27
  },
  "fs": null,
  "rs": null,
  "ssaw": 27.6,
  "ptbr": [
    2,
    9,
    15,
    3,
    4,
    10,
    18,
    22,
    25
  ],
  "sc": 0,
  "mi": 0,
  "wm": 1,
  "lwa": 27.6,
  "gwt": -1,
  "pmt": null,
  "ab": null,
  "ml": 2,
  "cs": 0.3,
  "rl": [
    9,
    10,
    4,
    5,
    5,
    9,
    5,
    8,
    3,
    4,
    5,
    6,
    8,
    2,
    8,
    4,
    10,
    8,
    5,
    8,
    6,
    2,
    5,
    2,
    10,
    5,
    2,
    5,
    6,
    4,
    9,
    10,
    8,
    6,
    9
  ],
  "ctw": 27.6,
  "cwc": 1,
  "fstc": null,
  "pcwc": 1,
  "rwsp": {
    "4": 6,
    "5": 10
  },
  "hashr": "0:9;8;8;2;6#10;3;4;5;4#4;4;10;2;9#5;5;8;10;10#5;6;5;5;8#9;8;8;2;6#5;2;6;5;9#R#4#021221#MV#12.0#MT#1#R#5#030413243134#MV#12.0#MT#1#MG#27.6#",
  "fb": null,
  "sid": "1981396352873004544",
  "psid": "1981396352873004544",
  "st": 1,
  "nst": 4,
  "pf": 2,
  "aw": 27.6,
  "wid": 0,
  "wt": "C",
  "wk": "0_C",
  "wbn": null,
  "wfg": null,
  "blb": 157786,
  "blab": 157774,
  "bl": 157801.6,
  "tb": 12,
  "tbb": 12,
  "tw": 27.6,
  "np": 15.6,
  "ocr": null,
  "mr": null,
  "ge": [
    1,
    11
  ]
}