{
  "wp": {
    "5": [
      2,
      10,
      19,
      22,
      23
    ],
    "8": [
      4,
      10,
      19
    ],
    "10": [
      1,
      3,
      9,
      10,
      19,
      24
    ]
  },
  "lw": {
    "5": 12,
    "8": 1.2,
    "10": 7.2
  },
  "orl": [
    9,
    10,
    5,
    10,
    8,
    9,
    5,
    8,
    9,
    10,
    0,
    3,
    3,
    6,
    8,
    1,
    4,
    4,
    4,
    0,
    10,
    2,
    5,
    5,
    10,
    2,
    2,
    5,
    9,
    9,
    3,
    8,
    4,
    9,
    6
  ],
  "snww": {
    "5": 2,
    "8": 1,
    "10": 4
  },
  "ssb": {
    "1": 21
  },
  "ss": {
    "1": 21
  },
  "fs": null,
  "rs": {
    "sspt": {},
    "rns": [
      [
        9,
        10
      ],
      [
        8
      ],
      [
        8
      ],
      [
        2
      ],
      []
    ],
    "rnss": [
      [],
      [],
      [],
      [
        0
      ],
      []
    ],
    "bsb": []
  },
  "ssaw": 439.8,
  "ptbr": [
    2,
    10,
    19,
    22,
    23,
    4,
    1,
    3,
    9,
    24
  ],
  "sc": 1,
  "mi": 3,
  "wm": 5,
  "lwa": 20.4,
  "gwt": 2,
  "pmt": null,
  "ab": null,
  "ml": 2,
  "cs": 0.3,
  "rl": [
    9,
    10,
    5,
    10,
    8,
    9,
    5,
    8,
    9,
    10,
    0,
    3,
    3,
    6,
    8,
    1,
    4,
    4,
    4,
    0,
    10,
    2,
    5,
    5,
    10,
    2,
    2,
    5,
    9,
    9,
    3,
    8,
    4,
    9,
    6
  ],
  "ctw": 102,
  "cwc": 7,
  "fstc": {
    "4": 6
  },
  "pcwc": 0,
  "rwsp": {
    "5": 10,
    "8": 2,
    "10": 3
  },
  "hashr": "6:9;8;8;2;9#10;9;1;5;9#5;10;4;5;3#10;0;4;10;8#8;3;4;2;4#9;3;0;2;9#5;6;10;5;6#R#5#0213253132#MV#0#MT#1#R#8#041325#MV#0#MT#1#R#10#010312132533#MV#0#MT#1#MG#102.0#",
  "fb": null,
  "sid": "1981175347541966336",
  "psid": "1981175277425786368",
  "st": 4,
  "nst": 4,
  "pf": 2,
  "aw": 439.8,
  "wid": 0,
  "wt": "C",
  "wk": "0_C",
  "wbn": null,
  "wfg": null,
  "blb": 127483,
  "blab": 127483,
  "bl": 127585,
  "tb": 0,
  "tbb": 12,
  "tw": 102,
  "np": 102,
  "ocr": null,
  "mr": null,
  "ge": [
    1,
    11
  ]
}