{
  "wp": {
    "8": [
      1,
      12,
      16
    ],
    "9": [
      3,
      12,
      18,
      26
    ]
  },
  "lw": {
    "8": 1.2,
    "9": 1.8
  },
  "orl": [
    6,
    8,
    7,
    9,
    7,
    6,
    9,
    4,
    7,
    10,
    3,
    10,
    0,
    5,
    9,
    2,
    8,
    5,
    9,
    6,
    5,
    9,
    6,
    3,
    7,
    10,
    9,
    4,
    5,
    5,
    7,
    2,
    10,
    10,
    4
  ],
  "snww": {
    "8": 1,
    "9": 1
  },
  "ssb": {
    "1": 10,
    "3": 13,
    "4": 18,
    "5": 20,
    "6": 24,
    "7": 27,
    "8": 14
  },
  "ss": {
    "1": 10,
    "3": 13,
    "5": 20,
    "6": 24,
    "7": 27,
    "8": 14
  },
  "fs": null,
  "rs": {
    "sspt": {
      "4": {
        "op": 17,
        "np": 18
      }
    },
    "rns": [
      [
        6
      ],
      [
        4
      ],
      [
        9
      ],
      [],
      []
    ],
    "rnss": [
      [],
      [],
      [
        0
      ],
      [],
      []
    ],
    "bsb": []
  },
  "ssaw": 13.2,
  "ptbr": [
    1,
    12,
    16,
    3,
    26
  ],
  "sc": 0,
  "mi": 1,
  "wm": 2,
  "lwa": 3,
  "gwt": -1,
  "pmt": null,
  "ab": null,
  "ml": 2,
  "cs": 0.3,
  "rl": [
    6,
    8,
    7,
    9,
    7,
    6,
    9,
    4,
    7,
    10,
    3,
    10,
    0,
    5,
    9,
    2,
    8,
    5,
    0,
    6,
    5,
    9,
    6,
    3,
    7,
    10,
    9,
    4,
    5,
    5,
    7,
    2,
    10,
    10,
    4
  ],
  "ctw": 6,
  "cwc": 2,
  "fstc": {
    "4": 1
  },
  "pcwc": 0,
  "rwsp": {
    "8": 2,
    "9": 3
  },
  "hashr": "1:6;4;9;9;5#8;7;2;6;5#7;10;8;3;7#9;3;5;7;2#7;10;0;10;10#6;0;6;9;10#9;5;5;4;4#R#8#011522#MV#0#MT#1#R#9#03152435#MV#0#MT#1#MG#6.0#",
  "fb": null,
  "sid": "1981266585892945408",
  "psid": "1981266570785062400",
  "st": 4,
  "nst": 4,
  "pf": 2,
  "aw": 13.2,
  "wid": 0,
  "wt": "C",
  "wk": "0_C",
  "wbn": null,
  "wfg": null,
  "blb": 120526,
  "blab": 120526,
  "bl": 120532,
  "tb": 0,
  "tbb": 12,
  "tw": 6,
  "np": 6,
  "ocr": null,
  "mr": null,
  "ge": [
    1,
    11
  ]
}